MANIFEST.in
README.md
setup.py
anonymizer/__init__.py
anonymizer/anonymDF.py
anonymizer/anonymity.py
anonymizer/config_anonymizer.py
anonymizer/diversity.py
anonymizer/transformations.py
anonymizer.egg-info/PKG-INFO
anonymizer.egg-info/SOURCES.txt
anonymizer.egg-info/dependency_links.txt
anonymizer.egg-info/entry_points.txt
anonymizer.egg-info/top_level.txt