Metadata-Version: 1.1
Name: anonymizer
Version: 0.0.6
Summary: Module de k-anonymisation
Home-page: https://github.com/SGMAP-AGD/anonymisation
Author: SGMAP-AGD
Author-email: plbithorel@gmail.com
License: UNKNOWN
Platform: UNKNOWN
Classifier: Programming Language :: Python
Classifier: Development Status :: 1 - Planning
Classifier: License :: OSI Approved :: GNU General Public License (GPL)
Classifier: Natural Language :: French
Classifier: Operating System :: OS Independent
Classifier: Programming Language :: Python :: 3
